{"type": "FeatureCollection", "features": [{"type": "Feature", "properties": {"filename": "DJI_20240830150420_0101_D.JPG", "prediction": "100.00%", "classification": "THIS PICTURE HAS Oak Wilt", "latitude": 43.125151583333334, "longitude": -86.25992527777778}, "geometry": {"type": "Point", "coordinates": [-86.25992527777778, 43.125151583333334]}}, {"type": "Feature", "properties": {"filename": "IMG_0025_2.jpg", "prediction": "100.00%", "classification": "THIS PICTURE HAS Oak Wilt", "latitude": 45.351338830555555, "longitude": -93.03056086}, "geometry": {"type": "Point", "coordinates": [-93.03056086, 45.351338830555555]}}, {"type": "Feature", "properties": {"filename": "IMG_0026_2.jpg", "prediction": "100.00%", "classification": "THIS PICTURE HAS Oak Wilt", "latitude": 45.35133723305556, "longitude": -93.0304473111111}, "geometry": {"type": "Point", "coordinates": [-93.0304473111111, 45.35133723305556]}}, {"type": "Feature", "properties": {"filename": "IMG_0028.jpg", "prediction": "100.00%", "classification": "THIS PICTURE HAS Oak Wilt", "latitude": 45.45036664194445, "longitude": -93.76471195555555}, "geometry": {"type": "Point", "coordinates": [-93.76471195555555, 45.45036664194445]}}, {"type": "Feature", "properties": {"filename": "IMG_0193_2.jpg", "prediction": "100.00%", "classification": "THIS PICTURE HAS Oak Wilt", "latitude": 45.35227093722222, "longitude": -93.02900241777778}, "geometry": {"type": "Point", "coordinates": [-93.02900241777778, 45.35227093722222]}}, {"type": "Feature", "properties": {"filename": "IMG_0193.jpg", "prediction": "100.00%", "classification": "THIS PICTURE HAS Oak Wilt", "latitude": 45.35227093722222, "longitude": -93.02900241777778}, "geometry": {"type": "Point", "coordinates": [-93.02900241777778, 45.35227093722222]}}]}